fastack_mail/__init__.py
fastack_mail/backend.py
fastack_mail/globals.py
fastack_mail/message.py
fastack_mail/sync.py
fastack_mail-0.1.0.dist-info/WHEEL
fastack_mail-0.1.0.dist-info/METADATA
fastack_mail-0.1.0.dist-info/RECORD
