Metadata-Version: 2.1
Name: fastack-mail
Version: 0.1.0
Summary: Simple plugin for sending email
Home-page: https://github.com/fastack-dev/fastack-mail
License: MIT
Author: aprilahijriyan
Author-email: hijriyan23@gmail.com
Maintainer: aprilahijriyan
Maintainer-email: 37798612+aprilahijriyan@users.noreply.github.com
Requires-Python: >=3.7,<3.10
Classifier: Development Status :: 4 - Beta
Classifier: Intended Audience :: Developers
Classifier: Intended Audience :: Information Technology
Classifier: Intended Audience :: System Administrators
Classifier: License :: OSI Approved :: MIT License
Classifier: Operating System :: OS Independent
Classifier: Programming Language :: Python
Classifier: Programming Language :: Python :: 3
Classifier: Programming Language :: Python :: 3 :: Only
Classifier: Programming Language :: Python :: 3.7
Classifier: Programming Language :: Python :: 3.8
Classifier: Programming Language :: Python :: 3.9
Classifier: Topic :: Internet
Classifier: Topic :: Software Development
Classifier: Topic :: Software Development :: Libraries
Classifier: Topic :: Software Development :: Libraries :: Python Modules
Requires-Dist: aiosmtplib (>=1.1.6,<2.0.0)
Requires-Dist: fastack (>=4.0.0,<5.0.0)
Requires-Dist: pydantic[email] (>=1.9.0,<2.0.0)
Project-URL: Bug Tracker, https://github.com/fastack-dev/fastack-mail/issues
Project-URL: Repository, https://github.com/fastack-dev/fastack-mail
